sandshrew/__init__.py
sandshrew/base_tool.py
sandshrew/data_types.py
sandshrew/helpers.py
sandshrew/llm_utils/__init__.py
sandshrew/llm_utils/openai.py
sandshrew-0.1.0.dist-info/licenses/LICENSE
sandshrew-0.1.0.dist-info/METADATA
sandshrew-0.1.0.dist-info/WHEEL
sandshrew-0.1.0.dist-info/top_level.txt
sandshrew-0.1.0.dist-info/RECORD
