Metadata-Version: 2.4
Name: sandshrew
Version: 0.1.0
Summary: Production-ready tool integration library for LLMs
Author-email: Kavya-24 <kavya@example.com>
License: LICENSE
Project-URL: Homepage, https://github.com/Kavya-24/sandshrew
Project-URL: Repository, https://github.com/Kavya-24/sandshrew.git
Project-URL: Documentation, https://github.com/Kavya-24/sandshrew#readme
Project-URL: Issues, https://github.com/Kavya-24/sandshrew/issues
Keywords: llm,tools,ai,integration
Classifier: Development Status :: 3 - Alpha
Classifier: Intended Audience :: Developers
Classifier: License :: OSI Approved :: MIT License
Classifier: Programming Language :: Python :: 3
Classifier: Programming Language :: Python :: 3.10
Classifier: Programming Language :: Python :: 3.11
Classifier: Programming Language :: Python :: 3.12
Classifier: Topic :: Software Development :: Libraries :: Python Modules
Requires-Python: >=3.10
License-File: LICENSE
Requires-Dist: pydantic>=2.0
Provides-Extra: dev
Requires-Dist: pytest>=7.0; extra == "dev"
Requires-Dist: ruff>=0.1.0; extra == "dev"
Dynamic: license-file
